LICENSE
MANIFEST.in
README
setup.py
lib/djtables/__init__.py
lib/djtables/__init__.pyc
lib/djtables/cell.py
lib/djtables/cell.pyc
lib/djtables/column.py
lib/djtables/column.pyc
lib/djtables/metatable.py
lib/djtables/metatable.pyc
lib/djtables/options.py
lib/djtables/options.pyc
lib/djtables/row.py
lib/djtables/row.pyc
lib/djtables/table.py
lib/djtables/table.pyc
lib/djtables/urls.py
lib/djtables/urls.pyc
lib/djtables.egg-info/PKG-INFO
lib/djtables.egg-info/SOURCES.txt
lib/djtables.egg-info/dependency_links.txt
lib/djtables.egg-info/requires.txt
lib/djtables.egg-info/top_level.txt
lib/djtables/templates/djtables/body.html
lib/djtables/templates/djtables/cols.html
lib/djtables/templates/djtables/foot.html
lib/djtables/templates/djtables/head.html
lib/djtables/templates/djtables/table.html
lib/djtables/templatetags/__init__.py
lib/djtables/templatetags/__init__.pyc
lib/djtables/templatetags/djtables_tags.py
lib/djtables/templatetags/djtables_tags.pyc