Metadata-Version: 1.0
Name: djtables
Version: 0.1.2
Summary: Declarative HTML table builder for Django
Home-page: http://github.com/adammck/djtables
Author: Adam Mckaig
Author-email: adam.mckaig@gmail.com
License: BSD
Platform: UNKNOWN
